{
  "芦山地震": {
    "href": "https://s.weibo.com/weibo?q=%E8%8A%A6%E5%B1%B1%E5%9C%B0%E9%9C%87&Refer=top",
    "hot": 17621662
  },
  "四川雅安芦山6.1级地震": {
    "href": "https://s.weibo.com/weibo?q=%23%E5%9B%9B%E5%B7%9D%E9%9B%85%E5%AE%89%E8%8A%A6%E5%B1%B16.1%E7%BA%A7%E5%9C%B0%E9%9C%87%23&Refer=top",
    "hot": 14266470
  },
  "成都震感": {
    "href": "https://s.weibo.com/weibo?q=%23%E6%88%90%E9%83%BD%E9%9C%87%E6%84%9F%23&Refer=top",
    "hot": 8261013
  },
  "云南洱源发生3.8级地震": {
    "href": "https://s.weibo.com/weibo?q=%23%E4%BA%91%E5%8D%97%E6%B4%B1%E6%BA%90%E5%8F%91%E7%94%9F3.8%E7%BA%A7%E5%9C%B0%E9%9C%87%23&Refer=top",
    "hot": 7372777
  },
  "Bin": {
    "href": "https://s.weibo.com/weibo?q=Bin&Refer=top",
    "hot": 5892975
  },
  "上海回来了": {
    "href": "https://s.weibo.com/weibo?q=%23%E4%B8%8A%E6%B5%B7%E5%9B%9E%E6%9D%A5%E4%BA%86%23&Refer=top",
    "hot": 4660739
  },
  "六一礼物": {
    "href": "https://s.weibo.com/weibo?q=%E5%85%AD%E4%B8%80%E7%A4%BC%E7%89%A9&Refer=top",
    "hot": 4336489
  },
  "妈妈给儿子买笔觉得图案辣眼睛": {
    "href": "https://s.weibo.com/weibo?q=%23%E5%A6%88%E5%A6%88%E7%BB%99%E5%84%BF%E5%AD%90%E4%B9%B0%E7%AC%94%E8%A7%89%E5%BE%97%E5%9B%BE%E6%A1%88%E8%BE%A3%E7%9C%BC%E7%9D%9B%23&Refer=top",
    "hot": 3862251
  },
  "芦山地震已致4死14伤": {
    "href": "https://s.weibo.com/weibo?q=%23%E8%8A%A6%E5%B1%B1%E5%9C%B0%E9%9C%87%E5%B7%B2%E8%87%B44%E6%AD%BB14%E4%BC%A4%23&Refer=top",
    "hot": 3826109
  },
  "儿童节快乐": {
    "href": "https://s.weibo.com/weibo?q=%E5%84%BF%E7%AB%A5%E8%8A%82%E5%BF%AB%E4%B9%90&Refer=top",
    "hot": 2841563
  },
  "这些新规6月起施行": {
    "href": "https://s.weibo.com/weibo?q=%23%E8%BF%99%E4%BA%9B%E6%96%B0%E8%A7%846%E6%9C%88%E8%B5%B7%E6%96%BD%E8%A1%8C%23&Refer=top",
    "hot": 2807158
  },
  "iPhone13": {
    "href": "https://s.weibo.com/weibo?q=%23iPhone13%23&Refer=top",
    "hot": 2786156
  },
  "患癌丈夫生前打赏女主播600万": {
    "href": "https://s.weibo.com/weibo?q=%23%E6%82%A3%E7%99%8C%E4%B8%88%E5%A4%AB%E7%94%9F%E5%89%8D%E6%89%93%E8%B5%8F%E5%A5%B3%E4%B8%BB%E6%92%AD600%E4%B8%87%23&Refer=top",
    "hot": 2747400
  },
  "618": {
    "href": "https://s.weibo.com/weibo?q=618&Refer=top",
    "hot": 2741947
  },
  "RNG": {
    "href": "https://s.weibo.com/weibo?q=%23RNG%23&Refer=top",
    "hot": 2588485
  },
  "反诈老陈被指连麦女主播做不雅动作": {
    "href": "https://s.weibo.com/weibo?q=%23%E5%8F%8D%E8%AF%88%E8%80%81%E9%99%88%E8%A2%AB%E6%8C%87%E8%BF%9E%E9%BA%A6%E5%A5%B3%E4%B8%BB%E6%92%AD%E5%81%9A%E4%B8%8D%E9%9B%85%E5%8A%A8%E4%BD%9C%23&Refer=top",
    "hot": 2570833
  },
  "童年专属BGM": {
    "href": "https://s.weibo.com/weibo?q=%23%E7%AB%A5%E5%B9%B4%E4%B8%93%E5%B1%9EBGM%23&Refer=top",
    "hot": 2457208
  },
  "Uzi": {
    "href": "https://s.weibo.com/weibo?q=Uzi&Refer=top",
    "hot": 2455092
  },
  "父母眼中多大都是孩子": {
    "href": "https://s.weibo.com/weibo?q=%23%E7%88%B6%E6%AF%8D%E7%9C%BC%E4%B8%AD%E5%A4%9A%E5%A4%A7%E9%83%BD%E6%98%AF%E5%AD%A9%E5%AD%90%23&Refer=top",
    "hot": 2440783
  },
  "iPhone4S和6S将被列入过时产品": {
    "href": "https://s.weibo.com/weibo?q=%23iPhone4S%E5%92%8C6S%E5%B0%86%E8%A2%AB%E5%88%97%E5%85%A5%E8%BF%87%E6%97%B6%E4%BA%A7%E5%93%81%23&Refer=top",
    "hot": 2394762
  },
  "小时候最喜欢的动画片": {
    "href": "https://s.weibo.com/weibo?q=%23%E5%B0%8F%E6%97%B6%E5%80%99%E6%9C%80%E5%96%9C%E6%AC%A2%E7%9A%84%E5%8A%A8%E7%94%BB%E7%89%87%23&Refer=top",
    "hot": 2289620
  },
  "BLG": {
    "href": "https://s.weibo.com/weibo?q=BLG&Refer=top",
    "hot": 2262398
  },
  "iPad": {
    "href": "https://s.weibo.com/weibo?q=%23iPad%23&Refer=top",
    "hot": 2193193
  },
  "上海致全市人民的感谢信": {
    "href": "https://s.weibo.com/weibo?q=%23%E4%B8%8A%E6%B5%B7%E8%87%B4%E5%85%A8%E5%B8%82%E4%BA%BA%E6%B0%91%E7%9A%84%E6%84%9F%E8%B0%A2%E4%BF%A1%23&Refer=top",
    "hot": 2019172
  },
  "003": {
    "href": "https://s.weibo.com/weibo?q=003&Refer=top",
    "hot": 2013318
  },
  "地震预警": {
    "href": "https://s.weibo.com/weibo?q=%23%E5%9C%B0%E9%9C%87%E9%A2%84%E8%AD%A6%23&Refer=top",
    "hot": 1909093
  },
  "中国少年图鉴": {
    "href": "https://s.weibo.com/weibo?q=%23%E4%B8%AD%E5%9B%BD%E5%B0%91%E5%B9%B4%E5%9B%BE%E9%89%B4%23&Refer=top",
    "hot": 1776405
  },
  "B站虚拟主播称消失半年是被拐卖": {
    "href": "https://s.weibo.com/weibo?q=%23B%E7%AB%99%E8%99%9A%E6%8B%9F%E4%B8%BB%E6%92%AD%E7%A7%B0%E6%B6%88%E5%A4%B1%E5%8D%8A%E5%B9%B4%E6%98%AF%E8%A2%AB%E6%8B%90%E5%8D%96%23&Refer=top",
    "hot": 1770208
  },
  "aespa新歌": {
    "href": "https://s.weibo.com/weibo?q=%23aespa%E6%96%B0%E6%AD%8C%23&Refer=top",
    "hot": 1753804
  },
  "防弹少年团现身白宫记者会": {
    "href": "https://s.weibo.com/weibo?q=%23%E9%98%B2%E5%BC%B9%E5%B0%91%E5%B9%B4%E5%9B%A2%E7%8E%B0%E8%BA%AB%E7%99%BD%E5%AE%AB%E8%AE%B0%E8%80%85%E4%BC%9A%23&Refer=top",
    "hot": 1737196
  },
  "上海检察院检察长张本才被查": {
    "href": "https://s.weibo.com/weibo?q=%23%E4%B8%8A%E6%B5%B7%E6%A3%80%E5%AF%9F%E9%99%A2%E6%A3%80%E5%AF%9F%E9%95%BF%E5%BC%A0%E6%9C%AC%E6%89%8D%E8%A2%AB%E6%9F%A5%23&Refer=top",
    "hot": 1712587
  },
  "小米电视再被曝屏幕自动脱落": {
    "href": "https://s.weibo.com/weibo?q=%23%E5%B0%8F%E7%B1%B3%E7%94%B5%E8%A7%86%E5%86%8D%E8%A2%AB%E6%9B%9D%E5%B1%8F%E5%B9%95%E8%87%AA%E5%8A%A8%E8%84%B1%E8%90%BD%23&Refer=top",
    "hot": 1537111
  },
  "六月": {
    "href": "https://s.weibo.com/weibo?q=%E5%85%AD%E6%9C%88&Refer=top",
    "hot": 1471985
  },
  "四川多地震感强烈": {
    "href": "https://s.weibo.com/weibo?q=%23%E5%9B%9B%E5%B7%9D%E5%A4%9A%E5%9C%B0%E9%9C%87%E6%84%9F%E5%BC%BA%E7%83%88%23&Refer=top",
    "hot": 1429330
  },
  "宝可梦": {
    "href": "https://s.weibo.com/weibo?q=%E5%AE%9D%E5%8F%AF%E6%A2%A6&Refer=top",
    "hot": 1406561
  },
  "李宁": {
    "href": "https://s.weibo.com/weibo?q=%E6%9D%8E%E5%AE%81&Refer=top",
    "hot": 1394798
  },
  "iPad中国大陆出货量暴跌近3成": {
    "href": "https://s.weibo.com/weibo?q=%23iPad%E4%B8%AD%E5%9B%BD%E5%A4%A7%E9%99%86%E5%87%BA%E8%B4%A7%E9%87%8F%E6%9A%B4%E8%B7%8C%E8%BF%913%E6%88%90%23&Refer=top",
    "hot": 1376051
  },
  "今起上海全面恢复正常生产生活秩序": {
    "href": "https://s.weibo.com/weibo?q=%23%E4%BB%8A%E8%B5%B7%E4%B8%8A%E6%B5%B7%E5%85%A8%E9%9D%A2%E6%81%A2%E5%A4%8D%E6%AD%A3%E5%B8%B8%E7%94%9F%E4%BA%A7%E7%94%9F%E6%B4%BB%E7%A7%A9%E5%BA%8F%23&Refer=top",
    "hot": 1288662
  },
  "芦山6.1级地震为2013年地震余震": {
    "href": "https://s.weibo.com/weibo?q=%23%E8%8A%A6%E5%B1%B16.1%E7%BA%A7%E5%9C%B0%E9%9C%87%E4%B8%BA2013%E5%B9%B4%E5%9C%B0%E9%9C%87%E4%BD%99%E9%9C%87%23&Refer=top",
    "hot": 1287740
  },
  "六一儿童节": {
    "href": "https://s.weibo.com/weibo?q=%23%E5%85%AD%E4%B8%80%E5%84%BF%E7%AB%A5%E8%8A%82%23&Refer=top",
    "hot": 1279323
  },
  "地震致宝兴1人遇难": {
    "href": "https://s.weibo.com/weibo?q=%23%E5%9C%B0%E9%9C%87%E8%87%B4%E5%AE%9D%E5%85%B41%E4%BA%BA%E9%81%87%E9%9A%BE%23&Refer=top",
    "hot": 1247559
  },
  "吉林四平删除两次以上未测核酸拘留罚款通报": {
    "href": "https://s.weibo.com/weibo?q=%23%E5%90%89%E6%9E%97%E5%9B%9B%E5%B9%B3%E5%88%A0%E9%99%A4%E4%B8%A4%E6%AC%A1%E4%BB%A5%E4%B8%8A%E6%9C%AA%E6%B5%8B%E6%A0%B8%E9%85%B8%E6%8B%98%E7%95%99%E7%BD%9A%E6%AC%BE%E9%80%9A%E6%8A%A5%23&Refer=top",
    "hot": 1246907
  },
  "男子撞兰博基尼下跪求饶转头炫耀": {
    "href": "https://s.weibo.com/weibo?q=%23%E7%94%B7%E5%AD%90%E6%92%9E%E5%85%B0%E5%8D%9A%E5%9F%BA%E5%B0%BC%E4%B8%8B%E8%B7%AA%E6%B1%82%E9%A5%B6%E8%BD%AC%E5%A4%B4%E7%82%AB%E8%80%80%23&Refer=top",
    "hot": 1246452
  },
  "重庆茶颜悦色": {
    "href": "https://s.weibo.com/weibo?q=%23%E9%87%8D%E5%BA%86%E8%8C%B6%E9%A2%9C%E6%82%A6%E8%89%B2%23&Refer=top",
    "hot": 1150284
  },
  "付尾款": {
    "href": "https://s.weibo.com/weibo?q=%23%E4%BB%98%E5%B0%BE%E6%AC%BE%23&Refer=top",
    "hot": 1134469
  },
  "重庆震感": {
    "href": "https://s.weibo.com/weibo?q=%23%E9%87%8D%E5%BA%86%E9%9C%87%E6%84%9F%23&Refer=top",
    "hot": 1092388
  },
  "山东专升本": {
    "href": "https://s.weibo.com/weibo?q=%23%E5%B1%B1%E4%B8%9C%E4%B8%93%E5%8D%87%E6%9C%AC%23&Refer=top",
    "hot": 1081071
  },
  "女儿超市买零食爸爸掌掴收银员": {
    "href": "https://s.weibo.com/weibo?q=%23%E5%A5%B3%E5%84%BF%E8%B6%85%E5%B8%82%E4%B9%B0%E9%9B%B6%E9%A3%9F%E7%88%B8%E7%88%B8%E6%8E%8C%E6%8E%B4%E6%94%B6%E9%93%B6%E5%91%98%23&Refer=top",
    "hot": 1043964
  },
  "四川雅安5分钟连发两次地震": {
    "href": "https://s.weibo.com/weibo?q=%23%E5%9B%9B%E5%B7%9D%E9%9B%85%E5%AE%895%E5%88%86%E9%92%9F%E8%BF%9E%E5%8F%91%E4%B8%A4%E6%AC%A1%E5%9C%B0%E9%9C%87%23&Refer=top",
    "hot": 1022602
  },
  "中小学教师性别严重失衡": {
    "href": "https://s.weibo.com/weibo?q=%23%E4%B8%AD%E5%B0%8F%E5%AD%A6%E6%95%99%E5%B8%88%E6%80%A7%E5%88%AB%E4%B8%A5%E9%87%8D%E5%A4%B1%E8%A1%A1%23&Refer=top",
    "hot": 1014921
  },
  "成都东站": {
    "href": "https://s.weibo.com/weibo?q=%E6%88%90%E9%83%BD%E4%B8%9C%E7%AB%99&Refer=top",
    "hot": 1005388
  },
  "Diya求婚成功": {
    "href": "https://s.weibo.com/weibo?q=%23Diya%E6%B1%82%E5%A9%9A%E6%88%90%E5%8A%9F%23&Refer=top",
    "hot": 965478
  },
  "姜云升 舞美": {
    "href": "https://s.weibo.com/weibo?q=%E5%A7%9C%E4%BA%91%E5%8D%87%20%E8%88%9E%E7%BE%8E&Refer=top",
    "hot": 957000
  },
  "童心未泯 世界皆甜": {
    "href": "https://s.weibo.com/weibo?q=%E7%AB%A5%E5%BF%83%E6%9C%AA%E6%B3%AF%20%E4%B8%96%E7%95%8C%E7%9A%86%E7%94%9C&Refer=top",
    "hot": 949386
  },
  "张文宏说比春天更宝贵的是人的生命": {
    "href": "https://s.weibo.com/weibo?q=%23%E5%BC%A0%E6%96%87%E5%AE%8F%E8%AF%B4%E6%AF%94%E6%98%A5%E5%A4%A9%E6%9B%B4%E5%AE%9D%E8%B4%B5%E7%9A%84%E6%98%AF%E4%BA%BA%E7%9A%84%E7%94%9F%E5%91%BD%23&Refer=top",
    "hot": 940235
  },
  "刘畊宏直播": {
    "href": "https://s.weibo.com/weibo?q=%E5%88%98%E7%95%8A%E5%AE%8F%E7%9B%B4%E6%92%AD&Refer=top",
    "hot": 901482
  },
  "老乡鸡董事长道歉": {
    "href": "https://s.weibo.com/weibo?q=%23%E8%80%81%E4%B9%A1%E9%B8%A1%E8%91%A3%E4%BA%8B%E9%95%BF%E9%81%93%E6%AD%89%23&Refer=top",
    "hot": 870450
  },
  "时代少年团舞出最美中国画": {
    "href": "https://s.weibo.com/weibo?q=%23%E6%97%B6%E4%BB%A3%E5%B0%91%E5%B9%B4%E5%9B%A2%E8%88%9E%E5%87%BA%E6%9C%80%E7%BE%8E%E4%B8%AD%E5%9B%BD%E7%94%BB%23&Refer=top",
    "hot": 867178
  },
  "你都多大了还看动画": {
    "href": "https://s.weibo.com/weibo?q=%23%E4%BD%A0%E9%83%BD%E5%A4%9A%E5%A4%A7%E4%BA%86%E8%BF%98%E7%9C%8B%E5%8A%A8%E7%94%BB%23&Refer=top",
    "hot": 850910
  },
  "告五人巡演": {
    "href": "https://s.weibo.com/weibo?q=%23%E5%91%8A%E4%BA%94%E4%BA%BA%E5%B7%A1%E6%BC%94%23&Refer=top",
    "hot": 849621
  },
  "上海好久不见": {
    "href": "https://s.weibo.com/weibo?q=%23%E4%B8%8A%E6%B5%B7%E5%A5%BD%E4%B9%85%E4%B8%8D%E8%A7%81%23&Refer=top",
    "hot": 841271
  },
  "成都两男子花三千打车到重庆偷手机": {
    "href": "https://s.weibo.com/weibo?q=%23%E6%88%90%E9%83%BD%E4%B8%A4%E7%94%B7%E5%AD%90%E8%8A%B1%E4%B8%89%E5%8D%83%E6%89%93%E8%BD%A6%E5%88%B0%E9%87%8D%E5%BA%86%E5%81%B7%E6%89%8B%E6%9C%BA%23&Refer=top",
    "hot": 817865
  },
  "BLG官宣Bin加入": {
    "href": "https://s.weibo.com/weibo?q=%23BLG%E5%AE%98%E5%AE%A3Bin%E5%8A%A0%E5%85%A5%23&Refer=top",
    "hot": 817069
  },
  "杨紫直播": {
    "href": "https://s.weibo.com/weibo?q=%E6%9D%A8%E7%B4%AB%E7%9B%B4%E6%92%AD&Refer=top",
    "hot": 816026
  },
  "上海核酸": {
    "href": "https://s.weibo.com/weibo?q=%E4%B8%8A%E6%B5%B7%E6%A0%B8%E9%85%B8&Refer=top",
    "hot": 783796
  },
  "RNG官宣Breathe加入": {
    "href": "https://s.weibo.com/weibo?q=%23RNG%E5%AE%98%E5%AE%A3Breathe%E5%8A%A0%E5%85%A5%23&Refer=top",
    "hot": 772806
  },
  "上海新增本土确诊5例无症状10例": {
    "href": "https://s.weibo.com/weibo?q=%23%E4%B8%8A%E6%B5%B7%E6%96%B0%E5%A2%9E%E6%9C%AC%E5%9C%9F%E7%A1%AE%E8%AF%8A5%E4%BE%8B%E6%97%A0%E7%97%87%E7%8A%B610%E4%BE%8B%23&Refer=top",
    "hot": 764584
  },
  "Fly": {
    "href": "https://s.weibo.com/weibo?q=Fly&Refer=top",
    "hot": 763022
  },
  "浙大毕业生卖营养土公司估值达10亿": {
    "href": "https://s.weibo.com/weibo?q=%23%E6%B5%99%E5%A4%A7%E6%AF%95%E4%B8%9A%E7%94%9F%E5%8D%96%E8%90%A5%E5%85%BB%E5%9C%9F%E5%85%AC%E5%8F%B8%E4%BC%B0%E5%80%BC%E8%BE%BE10%E4%BA%BF%23&Refer=top",
    "hot": 759467
  },
  "西安震感": {
    "href": "https://s.weibo.com/weibo?q=%23%E8%A5%BF%E5%AE%89%E9%9C%87%E6%84%9F%23&Refer=top",
    "hot": 739893
  },
  "官方回应山姆促销员因上厕所被辞退": {
    "href": "https://s.weibo.com/weibo?q=%23%E5%AE%98%E6%96%B9%E5%9B%9E%E5%BA%94%E5%B1%B1%E5%A7%86%E4%BF%83%E9%94%80%E5%91%98%E5%9B%A0%E4%B8%8A%E5%8E%95%E6%89%80%E8%A2%AB%E8%BE%9E%E9%80%80%23&Refer=top",
    "hot": 739054
  },
  "牺牲民警女儿遇警车立正敬礼": {
    "href": "https://s.weibo.com/weibo?q=%23%E7%89%BA%E7%89%B2%E6%B0%91%E8%AD%A6%E5%A5%B3%E5%84%BF%E9%81%87%E8%AD%A6%E8%BD%A6%E7%AB%8B%E6%AD%A3%E6%95%AC%E7%A4%BC%23&Refer=top",
    "hot": 728012
  },
  "腾讯开放降薪通道": {
    "href": "https://s.weibo.com/weibo?q=%23%E8%85%BE%E8%AE%AF%E5%BC%80%E6%94%BE%E9%99%8D%E8%96%AA%E9%80%9A%E9%81%93%23&Refer=top",
    "hot": 725695
  },
  "2022新一线城市名单官宣": {
    "href": "https://s.weibo.com/weibo?q=%232022%E6%96%B0%E4%B8%80%E7%BA%BF%E5%9F%8E%E5%B8%82%E5%90%8D%E5%8D%95%E5%AE%98%E5%AE%A3%23&Refer=top",
    "hot": 710120
  },
  "长沙早餐店燃爆事故致1名消防员牺牲": {
    "href": "https://s.weibo.com/weibo?q=%23%E9%95%BF%E6%B2%99%E6%97%A9%E9%A4%90%E5%BA%97%E7%87%83%E7%88%86%E4%BA%8B%E6%95%85%E8%87%B41%E5%90%8D%E6%B6%88%E9%98%B2%E5%91%98%E7%89%BA%E7%89%B2%23&Refer=top",
    "hot": 705817
  },
  "黄明昊 战至巅峰": {
    "href": "https://s.weibo.com/weibo?q=%E9%BB%84%E6%98%8E%E6%98%8A%20%E6%88%98%E8%87%B3%E5%B7%85%E5%B3%B0&Refer=top",
    "hot": 687281
  },
  "陕西人民教育出版社回应教辅图书插图问题": {
    "href": "https://s.weibo.com/weibo?q=%23%E9%99%95%E8%A5%BF%E4%BA%BA%E6%B0%91%E6%95%99%E8%82%B2%E5%87%BA%E7%89%88%E7%A4%BE%E5%9B%9E%E5%BA%94%E6%95%99%E8%BE%85%E5%9B%BE%E4%B9%A6%E6%8F%92%E5%9B%BE%E9%97%AE%E9%A2%98%23&Refer=top",
    "hot": 684706
  },
  "fgo": {
    "href": "https://s.weibo.com/weibo?q=fgo&Refer=top",
    "hot": 684264
  },
  "拜托她可是刘亦菲啊": {
    "href": "https://s.weibo.com/weibo?q=%23%E6%8B%9C%E6%89%98%E5%A5%B9%E5%8F%AF%E6%98%AF%E5%88%98%E4%BA%A6%E8%8F%B2%E5%95%8A%23&Refer=top",
    "hot": 680000
  },
  "50年后虚拟孩子将普及": {
    "href": "https://s.weibo.com/weibo?q=%2350%E5%B9%B4%E5%90%8E%E8%99%9A%E6%8B%9F%E5%AD%A9%E5%AD%90%E5%B0%86%E6%99%AE%E5%8F%8A%23&Refer=top",
    "hot": 675067
  },
  "温儒敏否认语文教材选编课文夹带私货": {
    "href": "https://s.weibo.com/weibo?q=%23%E6%B8%A9%E5%84%92%E6%95%8F%E5%90%A6%E8%AE%A4%E8%AF%AD%E6%96%87%E6%95%99%E6%9D%90%E9%80%89%E7%BC%96%E8%AF%BE%E6%96%87%E5%A4%B9%E5%B8%A6%E7%A7%81%E8%B4%A7%23&Refer=top",
    "hot": 668205
  },
  "援沪医疗队员撤离前留下自画像": {
    "href": "https://s.weibo.com/weibo?q=%23%E6%8F%B4%E6%B2%AA%E5%8C%BB%E7%96%97%E9%98%9F%E5%91%98%E6%92%A4%E7%A6%BB%E5%89%8D%E7%95%99%E4%B8%8B%E8%87%AA%E7%94%BB%E5%83%8F%23&Refer=top",
    "hot": 647175
  },
  "中免日上崩了": {
    "href": "https://s.weibo.com/weibo?q=%E4%B8%AD%E5%85%8D%E6%97%A5%E4%B8%8A%E5%B4%A9%E4%BA%86&Refer=top",
    "hot": 642218
  },
  "王者马超新皮肤": {
    "href": "https://s.weibo.com/weibo?q=%23%E7%8E%8B%E8%80%85%E9%A9%AC%E8%B6%85%E6%96%B0%E7%9A%AE%E8%82%A4%23&Refer=top",
    "hot": 639877
  },
  "那些念念不忘的童年美食": {
    "href": "https://s.weibo.com/weibo?q=%23%E9%82%A3%E4%BA%9B%E5%BF%B5%E5%BF%B5%E4%B8%8D%E5%BF%98%E7%9A%84%E7%AB%A5%E5%B9%B4%E7%BE%8E%E9%A3%9F%23&Refer=top",
    "hot": 632191
  },
  "年轻人为什么攒不下钱": {
    "href": "https://s.weibo.com/weibo?q=%23%E5%B9%B4%E8%BD%BB%E4%BA%BA%E4%B8%BA%E4%BB%80%E4%B9%88%E6%94%92%E4%B8%8D%E4%B8%8B%E9%92%B1%23&Refer=top",
    "hot": 629140
  },
  "北京5月31日新增14例本土确诊": {
    "href": "https://s.weibo.com/weibo?q=%23%E5%8C%97%E4%BA%AC5%E6%9C%8831%E6%97%A5%E6%96%B0%E5%A2%9E14%E4%BE%8B%E6%9C%AC%E5%9C%9F%E7%A1%AE%E8%AF%8A%23&Refer=top",
    "hot": 618922
  },
  "Xiaoxiang加入TT": {
    "href": "https://s.weibo.com/weibo?q=%23Xiaoxiang%E5%8A%A0%E5%85%A5TT%23&Refer=top",
    "hot": 618231
  },
  "维和防暴队将于未来几个月上映": {
    "href": "https://s.weibo.com/weibo?q=%23%E7%BB%B4%E5%92%8C%E9%98%B2%E6%9A%B4%E9%98%9F%E5%B0%86%E4%BA%8E%E6%9C%AA%E6%9D%A5%E5%87%A0%E4%B8%AA%E6%9C%88%E4%B8%8A%E6%98%A0%23&Refer=top",
    "hot": 608998
  },
  "央视六一": {
    "href": "https://s.weibo.com/weibo?q=%23%E5%A4%AE%E8%A7%86%E5%85%AD%E4%B8%80%23&Refer=top",
    "hot": 603635
  },
  "男子抽中千元奖品妻子转手退掉": {
    "href": "https://s.weibo.com/weibo?q=%23%E7%94%B7%E5%AD%90%E6%8A%BD%E4%B8%AD%E5%8D%83%E5%85%83%E5%A5%96%E5%93%81%E5%A6%BB%E5%AD%90%E8%BD%AC%E6%89%8B%E9%80%80%E6%8E%89%23&Refer=top",
    "hot": 597428
  },
  "成都一罐车撞塌收费站桥墩": {
    "href": "https://s.weibo.com/weibo?q=%23%E6%88%90%E9%83%BD%E4%B8%80%E7%BD%90%E8%BD%A6%E6%92%9E%E5%A1%8C%E6%94%B6%E8%B4%B9%E7%AB%99%E6%A1%A5%E5%A2%A9%23&Refer=top",
    "hot": 594920
  },
  "咪咕": {
    "href": "https://s.weibo.com/weibo?q=%E5%92%AA%E5%92%95&Refer=top",
    "hot": 594364
  },
  "童年照": {
    "href": "https://s.weibo.com/weibo?q=%E7%AB%A5%E5%B9%B4%E7%85%A7&Refer=top",
    "hot": 584619
  },
  "六一文案": {
    "href": "https://s.weibo.com/weibo?q=%23%E5%85%AD%E4%B8%80%E6%96%87%E6%A1%88%23&Refer=top",
    "hot": 584383
  },
  "上海烟花": {
    "href": "https://s.weibo.com/weibo?q=%E4%B8%8A%E6%B5%B7%E7%83%9F%E8%8A%B1&Refer=top",
    "hot": 564052
  },
  "五月的每天都是五月天": {
    "href": "https://s.weibo.com/weibo?q=%23%E4%BA%94%E6%9C%88%E7%9A%84%E6%AF%8F%E5%A4%A9%E9%83%BD%E6%98%AF%E4%BA%94%E6%9C%88%E5%A4%A9%23&Refer=top",
    "hot": 562934
  },
  "曾经有一个假期叫麦假": {
    "href": "https://s.weibo.com/weibo?q=%23%E6%9B%BE%E7%BB%8F%E6%9C%89%E4%B8%80%E4%B8%AA%E5%81%87%E6%9C%9F%E5%8F%AB%E9%BA%A6%E5%81%87%23&Refer=top",
    "hot": 562557
  },
  "暗夜行者 反转": {
    "href": "https://s.weibo.com/weibo?q=%E6%9A%97%E5%A4%9C%E8%A1%8C%E8%80%85%20%E5%8F%8D%E8%BD%AC&Refer=top",
    "hot": 562215
  },
  "摩尔庄园": {
    "href": "https://s.weibo.com/weibo?q=%23%E6%91%A9%E5%B0%94%E5%BA%84%E5%9B%AD%23&Refer=top",
    "hot": 555746
  },
  "赵睿": {
    "href": "https://s.weibo.com/weibo?q=%23%E8%B5%B5%E7%9D%BF%23&Refer=top",
    "hot": 552360
  },
  "赵丽颖录制开始推理吧": {
    "href": "https://s.weibo.com/weibo?q=%23%E8%B5%B5%E4%B8%BD%E9%A2%96%E5%BD%95%E5%88%B6%E5%BC%80%E5%A7%8B%E6%8E%A8%E7%90%86%E5%90%A7%23&Refer=top",
    "hot": 548734
  },
  "BLG官宣Uzi离队": {
    "href": "https://s.weibo.com/weibo?q=%23BLG%E5%AE%98%E5%AE%A3Uzi%E7%A6%BB%E9%98%9F%23&Refer=top",
    "hot": 544151
  },
  "上海恢复后外滩等地出现拥堵": {
    "href": "https://s.weibo.com/weibo?q=%23%E4%B8%8A%E6%B5%B7%E6%81%A2%E5%A4%8D%E5%90%8E%E5%A4%96%E6%BB%A9%E7%AD%89%E5%9C%B0%E5%87%BA%E7%8E%B0%E6%8B%A5%E5%A0%B5%23&Refer=top",
    "hot": 542112
  },
  "张杰直播": {
    "href": "https://s.weibo.com/weibo?q=%23%E5%BC%A0%E6%9D%B0%E7%9B%B4%E6%92%AD%23&Refer=top",
    "hot": 542088
  },
  "北京第352场疫情防控新闻发布会": {
    "href": "https://s.weibo.com/weibo?q=%23%E5%8C%97%E4%BA%AC%E7%AC%AC352%E5%9C%BA%E7%96%AB%E6%83%85%E9%98%B2%E6%8E%A7%E6%96%B0%E9%97%BB%E5%8F%91%E5%B8%83%E4%BC%9A%23&Refer=top",
    "hot": 538654
  },
  "离婚前需要做什么准备": {
    "href": "https://s.weibo.com/weibo?q=%23%E7%A6%BB%E5%A9%9A%E5%89%8D%E9%9C%80%E8%A6%81%E5%81%9A%E4%BB%80%E4%B9%88%E5%87%86%E5%A4%87%23&Refer=top",
    "hot": 535426
  },
  "法国禁止电子游戏中使用英语术语": {
    "href": "https://s.weibo.com/weibo?q=%23%E6%B3%95%E5%9B%BD%E7%A6%81%E6%AD%A2%E7%94%B5%E5%AD%90%E6%B8%B8%E6%88%8F%E4%B8%AD%E4%BD%BF%E7%94%A8%E8%8B%B1%E8%AF%AD%E6%9C%AF%E8%AF%AD%23&Refer=top",
    "hot": 534913
  },
  "谁能比疫情数据跑得更快": {
    "href": "https://s.weibo.com/weibo?q=%23%E8%B0%81%E8%83%BD%E6%AF%94%E7%96%AB%E6%83%85%E6%95%B0%E6%8D%AE%E8%B7%91%E5%BE%97%E6%9B%B4%E5%BF%AB%23&Refer=top",
    "hot": 534642
  },
  "地震时女生们扶脚伤同学撤离": {
    "href": "https://s.weibo.com/weibo?q=%23%E5%9C%B0%E9%9C%87%E6%97%B6%E5%A5%B3%E7%94%9F%E4%BB%AC%E6%89%B6%E8%84%9A%E4%BC%A4%E5%90%8C%E5%AD%A6%E6%92%A4%E7%A6%BB%23&Refer=top",
    "hot": 534458
  },
  "专场杨幂讲有个警察父亲是什么体验": {
    "href": "https://s.weibo.com/weibo?q=%23%E4%B8%93%E5%9C%BA%E6%9D%A8%E5%B9%82%E8%AE%B2%E6%9C%89%E4%B8%AA%E8%AD%A6%E5%AF%9F%E7%88%B6%E4%BA%B2%E6%98%AF%E4%BB%80%E4%B9%88%E4%BD%93%E9%AA%8C%23&Refer=top",
    "hot": 534199
  },
  "四川学生遇地震全班1秒钟避险": {
    "href": "https://s.weibo.com/weibo?q=%23%E5%9B%9B%E5%B7%9D%E5%AD%A6%E7%94%9F%E9%81%87%E5%9C%B0%E9%9C%87%E5%85%A8%E7%8F%AD1%E7%A7%92%E9%92%9F%E9%81%BF%E9%99%A9%23&Refer=top",
    "hot": 529231
  },
  "法网纳达尔淘汰德约科维奇进四强": {
    "href": "https://s.weibo.com/weibo?q=%23%E6%B3%95%E7%BD%91%E7%BA%B3%E8%BE%BE%E5%B0%94%E6%B7%98%E6%B1%B0%E5%BE%B7%E7%BA%A6%E7%A7%91%E7%BB%B4%E5%A5%87%E8%BF%9B%E5%9B%9B%E5%BC%BA%23&Refer=top",
    "hot": 520837
  },
  "东部战区在台岛周边海空域组织战备警巡": {
    "href": "https://s.weibo.com/weibo?q=%23%E4%B8%9C%E9%83%A8%E6%88%98%E5%8C%BA%E5%9C%A8%E5%8F%B0%E5%B2%9B%E5%91%A8%E8%BE%B9%E6%B5%B7%E7%A9%BA%E5%9F%9F%E7%BB%84%E7%BB%87%E6%88%98%E5%A4%87%E8%AD%A6%E5%B7%A1%23&Refer=top",
    "hot": 500333
  },
  "六一宝宝节": {
    "href": "https://s.weibo.com/weibo?q=%23%E5%85%AD%E4%B8%80%E5%AE%9D%E5%AE%9D%E8%8A%82%23&Refer=top",
    "hot": 497793
  },
  "刘亦菲分享迪士尼vlog": {
    "href": "https://s.weibo.com/weibo?q=%23%E5%88%98%E4%BA%A6%E8%8F%B2%E5%88%86%E4%BA%AB%E8%BF%AA%E5%A3%AB%E5%B0%BCvlog%23&Refer=top",
    "hot": 495806
  },
  "打卡6月第一天的上海": {
    "href": "https://s.weibo.com/weibo?q=%23%E6%89%93%E5%8D%A16%E6%9C%88%E7%AC%AC%E4%B8%80%E5%A4%A9%E7%9A%84%E4%B8%8A%E6%B5%B7%23&Refer=top",
    "hot": 493178
  },
  "上海居民12点准时走出小区": {
    "href": "https://s.weibo.com/weibo?q=%23%E4%B8%8A%E6%B5%B7%E5%B1%85%E6%B0%9112%E7%82%B9%E5%87%86%E6%97%B6%E8%B5%B0%E5%87%BA%E5%B0%8F%E5%8C%BA%23&Refer=top",
    "hot": 492001
  },
  "沈阳首次跌出新一线排名": {
    "href": "https://s.weibo.com/weibo?q=%23%E6%B2%88%E9%98%B3%E9%A6%96%E6%AC%A1%E8%B7%8C%E5%87%BA%E6%96%B0%E4%B8%80%E7%BA%BF%E6%8E%92%E5%90%8D%23&Refer=top",
    "hot": 487852
  },
  "国家地震三级应急响应": {
    "href": "https://s.weibo.com/weibo?q=%23%E5%9B%BD%E5%AE%B6%E5%9C%B0%E9%9C%87%E4%B8%89%E7%BA%A7%E5%BA%94%E6%80%A5%E5%93%8D%E5%BA%94%23&Refer=top",
    "hot": 471495
  },
  "匹诺曹定档": {
    "href": "https://s.weibo.com/weibo?q=%23%E5%8C%B9%E8%AF%BA%E6%9B%B9%E5%AE%9A%E6%A1%A3%23&Refer=top",
    "hot": 467692
  },
  "强制报告挺身而出为孩子们发声": {
    "href": "https://s.weibo.com/weibo?q=%23%E5%BC%BA%E5%88%B6%E6%8A%A5%E5%91%8A%E6%8C%BA%E8%BA%AB%E8%80%8C%E5%87%BA%E4%B8%BA%E5%AD%A9%E5%AD%90%E4%BB%AC%E5%8F%91%E5%A3%B0%23&Refer=top",
    "hot": 463542
  },
  "真正的养成系之光": {
    "href": "https://s.weibo.com/weibo?q=%23%E7%9C%9F%E6%AD%A3%E7%9A%84%E5%85%BB%E6%88%90%E7%B3%BB%E4%B9%8B%E5%85%89%23&Refer=top",
    "hot": 456538
  },
  "上海海昌海洋公园免费8天": {
    "href": "https://s.weibo.com/weibo?q=%23%E4%B8%8A%E6%B5%B7%E6%B5%B7%E6%98%8C%E6%B5%B7%E6%B4%8B%E5%85%AC%E5%9B%AD%E5%85%8D%E8%B4%B98%E5%A4%A9%23&Refer=top",
    "hot": 452617
  },
  "EDG官宣JunJia回归": {
    "href": "https://s.weibo.com/weibo?q=%23EDG%E5%AE%98%E5%AE%A3JunJia%E5%9B%9E%E5%BD%92%23&Refer=top",
    "hot": 449886
  },
  "爸爸穿裙子示范教女儿防走光": {
    "href": "https://s.weibo.com/weibo?q=%23%E7%88%B8%E7%88%B8%E7%A9%BF%E8%A3%99%E5%AD%90%E7%A4%BA%E8%8C%83%E6%95%99%E5%A5%B3%E5%84%BF%E9%98%B2%E8%B5%B0%E5%85%89%23&Refer=top",
    "hot": 449874
  },
  "可达鸭": {
    "href": "https://s.weibo.com/weibo?q=%E5%8F%AF%E8%BE%BE%E9%B8%AD&Refer=top",
    "hot": 445637
  },
  "北京通州台湖镇为封控高考生送来状元粽": {
    "href": "https://s.weibo.com/weibo?q=%23%E5%8C%97%E4%BA%AC%E9%80%9A%E5%B7%9E%E5%8F%B0%E6%B9%96%E9%95%87%E4%B8%BA%E5%B0%81%E6%8E%A7%E9%AB%98%E8%80%83%E7%94%9F%E9%80%81%E6%9D%A5%E7%8A%B6%E5%85%83%E7%B2%BD%23&Refer=top",
    "hot": 431762
  },
  "比亚迪将举报黑公关奖励调整为最高500万": {
    "href": "https://s.weibo.com/weibo?q=%23%E6%AF%94%E4%BA%9A%E8%BF%AA%E5%B0%86%E4%B8%BE%E6%8A%A5%E9%BB%91%E5%85%AC%E5%85%B3%E5%A5%96%E5%8A%B1%E8%B0%83%E6%95%B4%E4%B8%BA%E6%9C%80%E9%AB%98500%E4%B8%87%23&Refer=top",
    "hot": 431456
  },
  "Angelababy滑板的快乐": {
    "href": "https://s.weibo.com/weibo?q=%23Angelababy%E6%BB%91%E6%9D%BF%E7%9A%84%E5%BF%AB%E4%B9%90%23&Refer=top",
    "hot": 427805
  },
  "时代少年团六一儿童节祝福": {
    "href": "https://s.weibo.com/weibo?q=%23%E6%97%B6%E4%BB%A3%E5%B0%91%E5%B9%B4%E5%9B%A2%E5%85%AD%E4%B8%80%E5%84%BF%E7%AB%A5%E8%8A%82%E7%A5%9D%E7%A6%8F%23&Refer=top",
    "hot": 427496
  },
  "迪丽热巴晒童年照祝儿童节快乐": {
    "href": "https://s.weibo.com/weibo?q=%23%E8%BF%AA%E4%B8%BD%E7%83%AD%E5%B7%B4%E6%99%92%E7%AB%A5%E5%B9%B4%E7%85%A7%E7%A5%9D%E5%84%BF%E7%AB%A5%E8%8A%82%E5%BF%AB%E4%B9%90%23&Refer=top",
    "hot": 425788
  },
  "上海跨江桥隧路障拆除": {
    "href": "https://s.weibo.com/weibo?q=%23%E4%B8%8A%E6%B5%B7%E8%B7%A8%E6%B1%9F%E6%A1%A5%E9%9A%A7%E8%B7%AF%E9%9A%9C%E6%8B%86%E9%99%A4%23&Refer=top",
    "hot": 422444
  },
  "14岁女孩半夜渴醒误服饮料瓶中农药": {
    "href": "https://s.weibo.com/weibo?q=%2314%E5%B2%81%E5%A5%B3%E5%AD%A9%E5%8D%8A%E5%A4%9C%E6%B8%B4%E9%86%92%E8%AF%AF%E6%9C%8D%E9%A5%AE%E6%96%99%E7%93%B6%E4%B8%AD%E5%86%9C%E8%8D%AF%23&Refer=top",
    "hot": 422068
  },
  "任嘉伦直播": {
    "href": "https://s.weibo.com/weibo?q=%E4%BB%BB%E5%98%89%E4%BC%A6%E7%9B%B4%E6%92%AD&Refer=top",
    "hot": 418554
  },
  "林俊杰方回应": {
    "href": "https://s.weibo.com/weibo?q=%23%E6%9E%97%E4%BF%8A%E6%9D%B0%E6%96%B9%E5%9B%9E%E5%BA%94%23&Refer=top",
    "hot": 417915
  },
  "乘风破浪一公芭莎独白视频": {
    "href": "https://s.weibo.com/weibo?q=%23%E4%B9%98%E9%A3%8E%E7%A0%B4%E6%B5%AA%E4%B8%80%E5%85%AC%E8%8A%AD%E8%8E%8E%E7%8B%AC%E7%99%BD%E8%A7%86%E9%A2%91%23&Refer=top",
    "hot": 416011
  },
  "实拍上海街头": {
    "href": "https://s.weibo.com/weibo?q=%23%E5%AE%9E%E6%8B%8D%E4%B8%8A%E6%B5%B7%E8%A1%97%E5%A4%B4%23&Refer=top",
    "hot": 412975
  },
  "女子称因来姨妈上厕所次数多被裁": {
    "href": "https://s.weibo.com/weibo?q=%23%E5%A5%B3%E5%AD%90%E7%A7%B0%E5%9B%A0%E6%9D%A5%E5%A7%A8%E5%A6%88%E4%B8%8A%E5%8E%95%E6%89%80%E6%AC%A1%E6%95%B0%E5%A4%9A%E8%A2%AB%E8%A3%81%23&Refer=top",
    "hot": 412631
  },
  "迪丽热巴方辟谣": {
    "href": "https://s.weibo.com/weibo?q=%23%E8%BF%AA%E4%B8%BD%E7%83%AD%E5%B7%B4%E6%96%B9%E8%BE%9F%E8%B0%A3%23&Refer=top",
    "hot": 411733
  },
  "夏天不吃炸鸡吃什么": {
    "href": "https://s.weibo.com/weibo?q=%23%E5%A4%8F%E5%A4%A9%E4%B8%8D%E5%90%83%E7%82%B8%E9%B8%A1%E5%90%83%E4%BB%80%E4%B9%88%23&Refer=top",
    "hot": 408973
  },
  "白鹿六一晒九图plog": {
    "href": "https://s.weibo.com/weibo?q=%23%E7%99%BD%E9%B9%BF%E5%85%AD%E4%B8%80%E6%99%92%E4%B9%9D%E5%9B%BEplog%23&Refer=top",
    "hot": 405933
  },
  "电影一周的朋友定档625": {
    "href": "https://s.weibo.com/weibo?q=%23%E7%94%B5%E5%BD%B1%E4%B8%80%E5%91%A8%E7%9A%84%E6%9C%8B%E5%8F%8B%E5%AE%9A%E6%A1%A3625%23&Refer=top",
    "hot": 405881
  },
  "谁还不是宝宝": {
    "href": "https://s.weibo.com/weibo?q=%23%E8%B0%81%E8%BF%98%E4%B8%8D%E6%98%AF%E5%AE%9D%E5%AE%9D%23&Refer=top",
    "hot": 398829
  },
  "梦华录": {
    "href": "https://s.weibo.com/weibo?q=%23%E6%A2%A6%E5%8D%8E%E5%BD%95%23&Refer=top",
    "hot": 398722
  },
  "成年人的友情需不需要维系": {
    "href": "https://s.weibo.com/weibo?q=%23%E6%88%90%E5%B9%B4%E4%BA%BA%E7%9A%84%E5%8F%8B%E6%83%85%E9%9C%80%E4%B8%8D%E9%9C%80%E8%A6%81%E7%BB%B4%E7%B3%BB%23&Refer=top",
    "hot": 396919
  },
  "郑州部分核酸小屋7点开始": {
    "href": "https://s.weibo.com/weibo?q=%23%E9%83%91%E5%B7%9E%E9%83%A8%E5%88%86%E6%A0%B8%E9%85%B8%E5%B0%8F%E5%B1%8B7%E7%82%B9%E5%BC%80%E5%A7%8B%23&Refer=top",
    "hot": 392697
  },
  "北京社会面筛查发现2例感染者": {
    "href": "https://s.weibo.com/weibo?q=%23%E5%8C%97%E4%BA%AC%E7%A4%BE%E4%BC%9A%E9%9D%A2%E7%AD%9B%E6%9F%A5%E5%8F%91%E7%8E%B02%E4%BE%8B%E6%84%9F%E6%9F%93%E8%80%85%23&Refer=top",
    "hot": 392426
  },
  "一条plog告别五月": {
    "href": "https://s.weibo.com/weibo?q=%23%E4%B8%80%E6%9D%A1plog%E5%91%8A%E5%88%AB%E4%BA%94%E6%9C%88%23&Refer=top",
    "hot": 388480
  },
  "郑州小学生眼中的战疫": {
    "href": "https://s.weibo.com/weibo?q=%23%E9%83%91%E5%B7%9E%E5%B0%8F%E5%AD%A6%E7%94%9F%E7%9C%BC%E4%B8%AD%E7%9A%84%E6%88%98%E7%96%AB%23&Refer=top",
    "hot": 387693
  },
  "上海乘公交只扫一次码": {
    "href": "https://s.weibo.com/weibo?q=%23%E4%B8%8A%E6%B5%B7%E4%B9%98%E5%85%AC%E4%BA%A4%E5%8F%AA%E6%89%AB%E4%B8%80%E6%AC%A1%E7%A0%81%23&Refer=top",
    "hot": 385491
  },
  "黄明昊方澄清": {
    "href": "https://s.weibo.com/weibo?q=%23%E9%BB%84%E6%98%8E%E6%98%8A%E6%96%B9%E6%BE%84%E6%B8%85%23&Refer=top",
    "hot": 385320
  },
  "凑单": {
    "href": "https://s.weibo.com/weibo?q=%E5%87%91%E5%8D%95&Refer=top",
    "hot": 384291
  },
  "男子戴好口罩去搀扶被挡道盲人女子": {
    "href": "https://s.weibo.com/weibo?q=%23%E7%94%B7%E5%AD%90%E6%88%B4%E5%A5%BD%E5%8F%A3%E7%BD%A9%E5%8E%BB%E6%90%80%E6%89%B6%E8%A2%AB%E6%8C%A1%E9%81%93%E7%9B%B2%E4%BA%BA%E5%A5%B3%E5%AD%90%23&Refer=top",
    "hot": 384007
  },
  "许雅钧回应": {
    "href": "https://s.weibo.com/weibo?q=%23%E8%AE%B8%E9%9B%85%E9%92%A7%E5%9B%9E%E5%BA%94%23&Refer=top",
    "hot": 383701
  },
  "北京菜农送3500颗生菜感谢抗疫志愿者": {
    "href": "https://s.weibo.com/weibo?q=%23%E5%8C%97%E4%BA%AC%E8%8F%9C%E5%86%9C%E9%80%813500%E9%A2%97%E7%94%9F%E8%8F%9C%E6%84%9F%E8%B0%A2%E6%8A%97%E7%96%AB%E5%BF%97%E6%84%BF%E8%80%85%23&Refer=top",
    "hot": 382104
  },
  "芦山地震后画面": {
    "href": "https://s.weibo.com/weibo?q=%23%E8%8A%A6%E5%B1%B1%E5%9C%B0%E9%9C%87%E5%90%8E%E7%94%BB%E9%9D%A2%23&Refer=top",
    "hot": 379515
  },
  "华为成立第三批5个军团及系统部": {
    "href": "https://s.weibo.com/weibo?q=%23%E5%8D%8E%E4%B8%BA%E6%88%90%E7%AB%8B%E7%AC%AC%E4%B8%89%E6%89%B95%E4%B8%AA%E5%86%9B%E5%9B%A2%E5%8F%8A%E7%B3%BB%E7%BB%9F%E9%83%A8%23&Refer=top",
    "hot": 379044
  },
  "女孩表演节目10秒后趴舞台睡着": {
    "href": "https://s.weibo.com/weibo?q=%E5%A5%B3%E5%AD%A9%E8%A1%A8%E6%BC%94%E8%8A%82%E7%9B%AE10%E7%A7%92%E5%90%8E%E8%B6%B4%E8%88%9E%E5%8F%B0%E7%9D%A1%E7%9D%80&Refer=top",
    "hot": 374674
  },
  "遇地震暂时不要返回房间": {
    "href": "https://s.weibo.com/weibo?q=%23%E9%81%87%E5%9C%B0%E9%9C%87%E6%9A%82%E6%97%B6%E4%B8%8D%E8%A6%81%E8%BF%94%E5%9B%9E%E6%88%BF%E9%97%B4%23&Refer=top",
    "hot": 364718
  },
  "张光正花光积蓄给郑有恩买包": {
    "href": "https://s.weibo.com/weibo?q=%23%E5%BC%A0%E5%85%89%E6%AD%A3%E8%8A%B1%E5%85%89%E7%A7%AF%E8%93%84%E7%BB%99%E9%83%91%E6%9C%89%E6%81%A9%E4%B9%B0%E5%8C%85%23&Refer=top",
    "hot": 363642
  },
  "Jiejie在LPL登场三周年": {
    "href": "https://s.weibo.com/weibo?q=%23Jiejie%E5%9C%A8LPL%E7%99%BB%E5%9C%BA%E4%B8%89%E5%91%A8%E5%B9%B4%23&Refer=top",
    "hot": 362235
  },
  "当一颗西红柿长得太好看后": {
    "href": "https://s.weibo.com/weibo?q=%23%E5%BD%93%E4%B8%80%E9%A2%97%E8%A5%BF%E7%BA%A2%E6%9F%BF%E9%95%BF%E5%BE%97%E5%A4%AA%E5%A5%BD%E7%9C%8B%E5%90%8E%23&Refer=top",
    "hot": 360723
  },
  "理发成上海人头等大事": {
    "href": "https://s.weibo.com/weibo?q=%23%E7%90%86%E5%8F%91%E6%88%90%E4%B8%8A%E6%B5%B7%E4%BA%BA%E5%A4%B4%E7%AD%89%E5%A4%A7%E4%BA%8B%23&Refer=top",
    "hot": 356898
  },
  "武契奇宣誓就职": {
    "href": "https://s.weibo.com/weibo?q=%23%E6%AD%A6%E5%A5%91%E5%A5%87%E5%AE%A3%E8%AA%93%E5%B0%B1%E8%81%8C%23&Refer=top",
    "hot": 355755
  },
  "直击郑州常态化核酸首日现场": {
    "href": "https://s.weibo.com/weibo?q=%23%E7%9B%B4%E5%87%BB%E9%83%91%E5%B7%9E%E5%B8%B8%E6%80%81%E5%8C%96%E6%A0%B8%E9%85%B8%E9%A6%96%E6%97%A5%E7%8E%B0%E5%9C%BA%23&Refer=top",
    "hot": 355010
  },
  "王者荣耀": {
    "href": "https://s.weibo.com/weibo?q=%E7%8E%8B%E8%80%85%E8%8D%A3%E8%80%80&Refer=top",
    "hot": 354604
  },
  "网购洗衣机被要求出示房产证": {
    "href": "https://s.weibo.com/weibo?q=%23%E7%BD%91%E8%B4%AD%E6%B4%97%E8%A1%A3%E6%9C%BA%E8%A2%AB%E8%A6%81%E6%B1%82%E5%87%BA%E7%A4%BA%E6%88%BF%E4%BA%A7%E8%AF%81%23&Refer=top",
    "hot": 352395
  },
  "日本规定出售宠物需植入芯片": {
    "href": "https://s.weibo.com/weibo?q=%23%E6%97%A5%E6%9C%AC%E8%A7%84%E5%AE%9A%E5%87%BA%E5%94%AE%E5%AE%A0%E7%89%A9%E9%9C%80%E6%A4%8D%E5%85%A5%E8%8A%AF%E7%89%87%23&Refer=top",
    "hot": 351888
  },
  "王一博说我话不少我只是认生": {
    "href": "https://s.weibo.com/weibo?q=%23%E7%8E%8B%E4%B8%80%E5%8D%9A%E8%AF%B4%E6%88%91%E8%AF%9D%E4%B8%8D%E5%B0%91%E6%88%91%E5%8F%AA%E6%98%AF%E8%AE%A4%E7%94%9F%23&Refer=top",
    "hot": 345915
  },
  "不管几岁快乐万岁": {
    "href": "https://s.weibo.com/weibo?q=%23%E4%B8%8D%E7%AE%A1%E5%87%A0%E5%B2%81%E5%BF%AB%E4%B9%90%E4%B8%87%E5%B2%81%23&Refer=top",
    "hot": 343558
  },
  "金赛纶将被吊销驾照": {
    "href": "https://s.weibo.com/weibo?q=%23%E9%87%91%E8%B5%9B%E7%BA%B6%E5%B0%86%E8%A2%AB%E5%90%8A%E9%94%80%E9%A9%BE%E7%85%A7%23&Refer=top",
    "hot": 339966
  },
  "初一男孩午休认真看刑法": {
    "href": "https://s.weibo.com/weibo?q=%23%E5%88%9D%E4%B8%80%E7%94%B7%E5%AD%A9%E5%8D%88%E4%BC%91%E8%AE%A4%E7%9C%9F%E7%9C%8B%E5%88%91%E6%B3%95%23&Refer=top",
    "hot": 337635
  },
  "河北三河解除全域静态管理": {
    "href": "https://s.weibo.com/weibo?q=%23%E6%B2%B3%E5%8C%97%E4%B8%89%E6%B2%B3%E8%A7%A3%E9%99%A4%E5%85%A8%E5%9F%9F%E9%9D%99%E6%80%81%E7%AE%A1%E7%90%86%23&Refer=top",
    "hot": 336210
  },
  "短期内芦山余震区再发生更大地震可能性不大": {
    "href": "https://s.weibo.com/weibo?q=%23%E7%9F%AD%E6%9C%9F%E5%86%85%E8%8A%A6%E5%B1%B1%E4%BD%99%E9%9C%87%E5%8C%BA%E5%86%8D%E5%8F%91%E7%94%9F%E6%9B%B4%E5%A4%A7%E5%9C%B0%E9%9C%87%E5%8F%AF%E8%83%BD%E6%80%A7%E4%B8%8D%E5%A4%A7%23&Refer=top",
    "hot": 332360
  },
  "绵阳震感": {
    "href": "https://s.weibo.com/weibo?q=%E7%BB%B5%E9%98%B3%E9%9C%87%E6%84%9F&Refer=top",
    "hot": 328709
  },
  "真人版匹诺曹蓝仙女亮相": {
    "href": "https://s.weibo.com/weibo?q=%23%E7%9C%9F%E4%BA%BA%E7%89%88%E5%8C%B9%E8%AF%BA%E6%9B%B9%E8%93%9D%E4%BB%99%E5%A5%B3%E4%BA%AE%E7%9B%B8%23&Refer=top",
    "hot": 323456
  },
  "上海恢复后最想做的事": {
    "href": "https://s.weibo.com/weibo?q=%23%E4%B8%8A%E6%B5%B7%E6%81%A2%E5%A4%8D%E5%90%8E%E6%9C%80%E6%83%B3%E5%81%9A%E7%9A%84%E4%BA%8B%23&Refer=top",
    "hot": 318571
  },
  "雅安消防已集结出发赶赴震中": {
    "href": "https://s.weibo.com/weibo?q=%23%E9%9B%85%E5%AE%89%E6%B6%88%E9%98%B2%E5%B7%B2%E9%9B%86%E7%BB%93%E5%87%BA%E5%8F%91%E8%B5%B6%E8%B5%B4%E9%9C%87%E4%B8%AD%23&Refer=top",
    "hot": 318415
  },
  "虞书欣分享落日沙漠舞蹈视频": {
    "href": "https://s.weibo.com/weibo?q=%23%E8%99%9E%E4%B9%A6%E6%AC%A3%E5%88%86%E4%BA%AB%E8%90%BD%E6%97%A5%E6%B2%99%E6%BC%A0%E8%88%9E%E8%B9%88%E8%A7%86%E9%A2%91%23&Refer=top",
    "hot": 316903
  },
  "五十公里桃花坞2全阵容": {
    "href": "https://s.weibo.com/weibo?q=%23%E4%BA%94%E5%8D%81%E5%85%AC%E9%87%8C%E6%A1%83%E8%8A%B1%E5%9D%9E2%E5%85%A8%E9%98%B5%E5%AE%B9%23&Refer=top",
    "hot": 316226
  },
  "胡杏儿曾比特客厅演唱会": {
    "href": "https://s.weibo.com/weibo?q=%23%E8%83%A1%E6%9D%8F%E5%84%BF%E6%9B%BE%E6%AF%94%E7%89%B9%E5%AE%A2%E5%8E%85%E6%BC%94%E5%94%B1%E4%BC%9A%23&Refer=top",
    "hot": 314481
  },
  "愿四川平安": {
    "href": "https://s.weibo.com/weibo?q=%23%E6%84%BF%E5%9B%9B%E5%B7%9D%E5%B9%B3%E5%AE%89%23&Refer=top",
    "hot": 312879
  },
  "WBG夏季赛大名单": {
    "href": "https://s.weibo.com/weibo?q=WBG%E5%A4%8F%E5%AD%A3%E8%B5%9B%E5%A4%A7%E5%90%8D%E5%8D%95&Refer=top",
    "hot": 311964
  },
  "上海恢复后那些值得记住的瞬间": {
    "href": "https://s.weibo.com/weibo?q=%23%E4%B8%8A%E6%B5%B7%E6%81%A2%E5%A4%8D%E5%90%8E%E9%82%A3%E4%BA%9B%E5%80%BC%E5%BE%97%E8%AE%B0%E4%BD%8F%E7%9A%84%E7%9E%AC%E9%97%B4%23&Refer=top",
    "hot": 305626
  },
  "平常喊不慌的四川人这次全下楼了": {
    "href": "https://s.weibo.com/weibo?q=%23%E5%B9%B3%E5%B8%B8%E5%96%8A%E4%B8%8D%E6%85%8C%E7%9A%84%E5%9B%9B%E5%B7%9D%E4%BA%BA%E8%BF%99%E6%AC%A1%E5%85%A8%E4%B8%8B%E6%A5%BC%E4%BA%86%23&Refer=top",
    "hot": 305563
  },
  "总台六一节目单": {
    "href": "https://s.weibo.com/weibo?q=%23%E6%80%BB%E5%8F%B0%E5%85%AD%E4%B8%80%E8%8A%82%E7%9B%AE%E5%8D%95%23&Refer=top",
    "hot": 304198
  },
  "知情人士回应腾讯开放降薪通道": {
    "href": "https://s.weibo.com/weibo?q=%23%E7%9F%A5%E6%83%85%E4%BA%BA%E5%A3%AB%E5%9B%9E%E5%BA%94%E8%85%BE%E8%AE%AF%E5%BC%80%E6%94%BE%E9%99%8D%E8%96%AA%E9%80%9A%E9%81%93%23&Refer=top",
    "hot": 303486
  },
  "王心凌清唱yyds": {
    "href": "https://s.weibo.com/weibo?q=%23%E7%8E%8B%E5%BF%83%E5%87%8C%E6%B8%85%E5%94%B1yyds%23&Refer=top",
    "hot": 303143
  },
  "2022上半年最后1个月": {
    "href": "https://s.weibo.com/weibo?q=%232022%E4%B8%8A%E5%8D%8A%E5%B9%B4%E6%9C%80%E5%90%8E1%E4%B8%AA%E6%9C%88%23&Refer=top",
    "hot": 302420
  },
  "陈楚生陆虎给从前的自己": {
    "href": "https://s.weibo.com/weibo?q=%23%E9%99%88%E6%A5%9A%E7%94%9F%E9%99%86%E8%99%8E%E7%BB%99%E4%BB%8E%E5%89%8D%E7%9A%84%E8%87%AA%E5%B7%B1%23&Refer=top",
    "hot": 300778
  },
  "富士": {
    "href": "https://s.weibo.com/weibo?q=%E5%AF%8C%E5%A3%AB&Refer=top",
    "hot": 299869
  },
  "法网2022": {
    "href": "https://s.weibo.com/weibo?q=%23%E6%B3%95%E7%BD%912022%23&Refer=top",
    "hot": 298654
  },
  "小肚已接收扁平指令": {
    "href": "https://s.weibo.com/weibo?q=%23%E5%B0%8F%E8%82%9A%E5%B7%B2%E6%8E%A5%E6%94%B6%E6%89%81%E5%B9%B3%E6%8C%87%E4%BB%A4%23&Refer=top",
    "hot": 297547
  },
  "吴磊赵露思星汉灿烂月升沧海过审": {
    "href": "https://s.weibo.com/weibo?q=%23%E5%90%B4%E7%A3%8A%E8%B5%B5%E9%9C%B2%E6%80%9D%E6%98%9F%E6%B1%89%E7%81%BF%E7%83%82%E6%9C%88%E5%8D%87%E6%B2%A7%E6%B5%B7%E8%BF%87%E5%AE%A1%23&Refer=top",
    "hot": 297014
  },
  "被动物幼崽治愈了": {
    "href": "https://s.weibo.com/weibo?q=%23%E8%A2%AB%E5%8A%A8%E7%89%A9%E5%B9%BC%E5%B4%BD%E6%B2%BB%E6%84%88%E4%BA%86%23&Refer=top",
    "hot": 292805
  },
  "梦华录风华人物谱": {
    "href": "https://s.weibo.com/weibo?q=%23%E6%A2%A6%E5%8D%8E%E5%BD%95%E9%A3%8E%E5%8D%8E%E4%BA%BA%E7%89%A9%E8%B0%B1%23&Refer=top",
    "hot": 290155
  },
  "恋综cp鹅厂团建安排上了": {
    "href": "https://s.weibo.com/weibo?q=%23%E6%81%8B%E7%BB%BCcp%E9%B9%85%E5%8E%82%E5%9B%A2%E5%BB%BA%E5%AE%89%E6%8E%92%E4%B8%8A%E4%BA%86%23&Refer=top",
    "hot": 289246
  },
  "西出玉门": {
    "href": "https://s.weibo.com/weibo?q=%E8%A5%BF%E5%87%BA%E7%8E%89%E9%97%A8&Refer=top",
    "hot": 288554
  },
  "赵亚楠陆莹在一起了": {
    "href": "https://s.weibo.com/weibo?q=%23%E8%B5%B5%E4%BA%9A%E6%A5%A0%E9%99%86%E8%8E%B9%E5%9C%A8%E4%B8%80%E8%B5%B7%E4%BA%86%23&Refer=top",
    "hot": 288201
  },
  "男孩提醒跟孙悟空合影要收费遭恐吓": {
    "href": "https://s.weibo.com/weibo?q=%23%E7%94%B7%E5%AD%A9%E6%8F%90%E9%86%92%E8%B7%9F%E5%AD%99%E6%82%9F%E7%A9%BA%E5%90%88%E5%BD%B1%E8%A6%81%E6%94%B6%E8%B4%B9%E9%81%AD%E6%81%90%E5%90%93%23&Refer=top",
    "hot": 285194
  },
  "李旻浩新歌紫发好温柔": {
    "href": "https://s.weibo.com/weibo?q=%23%E6%9D%8E%E6%97%BB%E6%B5%A9%E6%96%B0%E6%AD%8C%E7%B4%AB%E5%8F%91%E5%A5%BD%E6%B8%A9%E6%9F%94%23&Refer=top",
    "hot": 283359
  },
  "成都市进一步优化完善房地产政策": {
    "href": "https://s.weibo.com/weibo?q=%23%E6%88%90%E9%83%BD%E5%B8%82%E8%BF%9B%E4%B8%80%E6%AD%A5%E4%BC%98%E5%8C%96%E5%AE%8C%E5%96%84%E6%88%BF%E5%9C%B0%E4%BA%A7%E6%94%BF%E7%AD%96%23&Refer=top",
    "hot": 281809
  },
  "赵小棠自己设计直播服装": {
    "href": "https://s.weibo.com/weibo?q=%23%E8%B5%B5%E5%B0%8F%E6%A3%A0%E8%87%AA%E5%B7%B1%E8%AE%BE%E8%AE%A1%E7%9B%B4%E6%92%AD%E6%9C%8D%E8%A3%85%23&Refer=top",
    "hot": 276977
  },
  "小学生带着警察去扫毒": {
    "href": "https://s.weibo.com/weibo?q=%23%E5%B0%8F%E5%AD%A6%E7%94%9F%E5%B8%A6%E7%9D%80%E8%AD%A6%E5%AF%9F%E5%8E%BB%E6%89%AB%E6%AF%92%23&Refer=top",
    "hot": 274030
  },
  "上海快递": {
    "href": "https://s.weibo.com/weibo?q=%E4%B8%8A%E6%B5%B7%E5%BF%AB%E9%80%92&Refer=top",
    "hot": 271133
  },
  "北京增7例本土感染者": {
    "href": "https://s.weibo.com/weibo?q=%23%E5%8C%97%E4%BA%AC%E5%A2%9E7%E4%BE%8B%E6%9C%AC%E5%9C%9F%E6%84%9F%E6%9F%93%E8%80%85%23&Refer=top",
    "hot": 270526
  },
  "你的童年回忆杀": {
    "href": "https://s.weibo.com/weibo?q=%23%E4%BD%A0%E7%9A%84%E7%AB%A5%E5%B9%B4%E5%9B%9E%E5%BF%86%E6%9D%80%23&Refer=top",
    "hot": 268462
  },
  "广东人大常委会副主任陈如桂被查": {
    "href": "https://s.weibo.com/weibo?q=%23%E5%B9%BF%E4%B8%9C%E4%BA%BA%E5%A4%A7%E5%B8%B8%E5%A7%94%E4%BC%9A%E5%89%AF%E4%B8%BB%E4%BB%BB%E9%99%88%E5%A6%82%E6%A1%82%E8%A2%AB%E6%9F%A5%23&Refer=top",
    "hot": 265456
  },
  "如何看待年轻人野性消费国货": {
    "href": "https://s.weibo.com/weibo?q=%23%E5%A6%82%E4%BD%95%E7%9C%8B%E5%BE%85%E5%B9%B4%E8%BD%BB%E4%BA%BA%E9%87%8E%E6%80%A7%E6%B6%88%E8%B4%B9%E5%9B%BD%E8%B4%A7%23&Refer=top",
    "hot": 264428
  },
  "你会陪喜欢的人做讨厌的事吗": {
    "href": "https://s.weibo.com/weibo?q=%23%E4%BD%A0%E4%BC%9A%E9%99%AA%E5%96%9C%E6%AC%A2%E7%9A%84%E4%BA%BA%E5%81%9A%E8%AE%A8%E5%8E%8C%E7%9A%84%E4%BA%8B%E5%90%97%23&Refer=top",
    "hot": 260670
  },
  "DK官宣hoya离队": {
    "href": "https://s.weibo.com/weibo?q=%23DK%E5%AE%98%E5%AE%A3hoya%E7%A6%BB%E9%98%9F%23&Refer=top",
    "hot": 259176
  },
  "小孩子看大人的问题有多简单": {
    "href": "https://s.weibo.com/weibo?q=%23%E5%B0%8F%E5%AD%A9%E5%AD%90%E7%9C%8B%E5%A4%A7%E4%BA%BA%E7%9A%84%E9%97%AE%E9%A2%98%E6%9C%89%E5%A4%9A%E7%AE%80%E5%8D%95%23&Refer=top",
    "hot": 257569
  },
  "端午假期北京继续暂停堂食": {
    "href": "https://s.weibo.com/weibo?q=%23%E7%AB%AF%E5%8D%88%E5%81%87%E6%9C%9F%E5%8C%97%E4%BA%AC%E7%BB%A7%E7%BB%AD%E6%9A%82%E5%81%9C%E5%A0%82%E9%A3%9F%23&Refer=top",
    "hot": 257404
  },
  "很喜欢文学": {
    "href": "https://s.weibo.com/weibo?q=%23%E5%BE%88%E5%96%9C%E6%AC%A2%E6%96%87%E5%AD%A6%23&Refer=top",
    "hot": 252656
  },
  "宜宾震感": {
    "href": "https://s.weibo.com/weibo?q=%E5%AE%9C%E5%AE%BE%E9%9C%87%E6%84%9F&Refer=top",
    "hot": 252321
  },
  "aespa将于7月8日回归": {
    "href": "https://s.weibo.com/weibo?q=%23aespa%E5%B0%86%E4%BA%8E7%E6%9C%888%E6%97%A5%E5%9B%9E%E5%BD%92%23&Refer=top",
    "hot": 251752
  },
  "贝尔官宣告别皇马": {
    "href": "https://s.weibo.com/weibo?q=%23%E8%B4%9D%E5%B0%94%E5%AE%98%E5%AE%A3%E5%91%8A%E5%88%AB%E7%9A%87%E9%A9%AC%23&Refer=top",
    "hot": 250938
  },
  "EDG官宣夏季赛大名单": {
    "href": "https://s.weibo.com/weibo?q=%23EDG%E5%AE%98%E5%AE%A3%E5%A4%8F%E5%AD%A3%E8%B5%9B%E5%A4%A7%E5%90%8D%E5%8D%95%23&Refer=top",
    "hot": 250393
  },
  "严禁以防疫为由不让农民下地种田": {
    "href": "https://s.weibo.com/weibo?q=%23%E4%B8%A5%E7%A6%81%E4%BB%A5%E9%98%B2%E7%96%AB%E4%B8%BA%E7%94%B1%E4%B8%8D%E8%AE%A9%E5%86%9C%E6%B0%91%E4%B8%8B%E5%9C%B0%E7%A7%8D%E7%94%B0%23&Refer=top",
    "hot": 247895
  },
  "为什么要拒绝恋爱脑": {
    "href": "https://s.weibo.com/weibo?q=%23%E4%B8%BA%E4%BB%80%E4%B9%88%E8%A6%81%E6%8B%92%E7%BB%9D%E6%81%8B%E7%88%B1%E8%84%91%23&Refer=top",
    "hot": 247645
  },
  "张芸京唱偏爱梦回仙剑三": {
    "href": "https://s.weibo.com/weibo?q=%23%E5%BC%A0%E8%8A%B8%E4%BA%AC%E5%94%B1%E5%81%8F%E7%88%B1%E6%A2%A6%E5%9B%9E%E4%BB%99%E5%89%91%E4%B8%89%23&Refer=top",
    "hot": 238893
  },
  "战至巅峰定档0611": {
    "href": "https://s.weibo.com/weibo?q=%23%E6%88%98%E8%87%B3%E5%B7%85%E5%B3%B0%E5%AE%9A%E6%A1%A30611%23&Refer=top",
    "hot": 229461
  },
  "过去一年四川有79次3级以上地震": {
    "href": "https://s.weibo.com/weibo?q=%23%E8%BF%87%E5%8E%BB%E4%B8%80%E5%B9%B4%E5%9B%9B%E5%B7%9D%E6%9C%8979%E6%AC%A13%E7%BA%A7%E4%BB%A5%E4%B8%8A%E5%9C%B0%E9%9C%87%23&Refer=top",
    "hot": 228150
  },
  "安贤洙的日常记录": {
    "href": "https://s.weibo.com/weibo?q=%23%E5%AE%89%E8%B4%A4%E6%B4%99%E7%9A%84%E6%97%A5%E5%B8%B8%E8%AE%B0%E5%BD%95%23&Refer=top",
    "hot": 227845
  },
  "郑有恩恋爱后拽姐变甜妹": {
    "href": "https://s.weibo.com/weibo?q=%23%E9%83%91%E6%9C%89%E6%81%A9%E6%81%8B%E7%88%B1%E5%90%8E%E6%8B%BD%E5%A7%90%E5%8F%98%E7%94%9C%E5%A6%B9%23&Refer=top",
    "hot": 225367
  },
  "84款APP存在侵害用户权益行为": {
    "href": "https://s.weibo.com/weibo?q=%2384%E6%AC%BEAPP%E5%AD%98%E5%9C%A8%E4%BE%B5%E5%AE%B3%E7%94%A8%E6%88%B7%E6%9D%83%E7%9B%8A%E8%A1%8C%E4%B8%BA%23&Refer=top",
    "hot": 224474
  },
  "林深见鹿追妻版预告": {
    "href": "https://s.weibo.com/weibo?q=%23%E6%9E%97%E6%B7%B1%E8%A7%81%E9%B9%BF%E8%BF%BD%E5%A6%BB%E7%89%88%E9%A2%84%E5%91%8A%23&Refer=top",
    "hot": 222999
  },
  "广东专插本": {
    "href": "https://s.weibo.com/weibo?q=%23%E5%B9%BF%E4%B8%9C%E4%B8%93%E6%8F%92%E6%9C%AC%23&Refer=top",
    "hot": 222164
  },
  "芦山地震山体滑坡画面": {
    "href": "https://s.weibo.com/weibo?q=%23%E8%8A%A6%E5%B1%B1%E5%9C%B0%E9%9C%87%E5%B1%B1%E4%BD%93%E6%BB%91%E5%9D%A1%E7%94%BB%E9%9D%A2%23&Refer=top",
    "hot": 220283
  },
  "消防员有多少小朋友被卡住的素材": {
    "href": "https://s.weibo.com/weibo?q=%23%E6%B6%88%E9%98%B2%E5%91%98%E6%9C%89%E5%A4%9A%E5%B0%91%E5%B0%8F%E6%9C%8B%E5%8F%8B%E8%A2%AB%E5%8D%A1%E4%BD%8F%E7%9A%84%E7%B4%A0%E6%9D%90%23&Refer=top",
    "hot": 217158
  },
  "瘦肚子最有效的三个动作": {
    "href": "https://s.weibo.com/weibo?q=%23%E7%98%A6%E8%82%9A%E5%AD%90%E6%9C%80%E6%9C%89%E6%95%88%E7%9A%84%E4%B8%89%E4%B8%AA%E5%8A%A8%E4%BD%9C%23&Refer=top",
    "hot": 215209
  },
  "2022年法考6月16日起报名": {
    "href": "https://s.weibo.com/weibo?q=%232022%E5%B9%B4%E6%B3%95%E8%80%836%E6%9C%8816%E6%97%A5%E8%B5%B7%E6%8A%A5%E5%90%8D%23&Refer=top",
    "hot": 211107
  },
  "川内高校地震疏散": {
    "href": "https://s.weibo.com/weibo?q=%23%E5%B7%9D%E5%86%85%E9%AB%98%E6%A0%A1%E5%9C%B0%E9%9C%87%E7%96%8F%E6%95%A3%23&Refer=top",
    "hot": 206310
  },
  "小樊振东又胖又听话": {
    "href": "https://s.weibo.com/weibo?q=%23%E5%B0%8F%E6%A8%8A%E6%8C%AF%E4%B8%9C%E5%8F%88%E8%83%96%E5%8F%88%E5%90%AC%E8%AF%9D%23&Refer=top",
    "hot": 205765
  },
  "鹿晗拍摄花絮视频": {
    "href": "https://s.weibo.com/weibo?q=%23%E9%B9%BF%E6%99%97%E6%8B%8D%E6%91%84%E8%8A%B1%E7%B5%AE%E8%A7%86%E9%A2%91%23&Refer=top",
    "hot": 202549
  },
  "李易峰骆翔完美诠释使命高于一切": {
    "href": "https://s.weibo.com/weibo?q=%23%E6%9D%8E%E6%98%93%E5%B3%B0%E9%AA%86%E7%BF%94%E5%AE%8C%E7%BE%8E%E8%AF%A0%E9%87%8A%E4%BD%BF%E5%91%BD%E9%AB%98%E4%BA%8E%E4%B8%80%E5%88%87%23&Refer=top",
    "hot": 200875
  },
  "一起去上海压马路": {
    "href": "https://s.weibo.com/weibo?q=%23%E4%B8%80%E8%B5%B7%E5%8E%BB%E4%B8%8A%E6%B5%B7%E5%8E%8B%E9%A9%AC%E8%B7%AF%23&Refer=top",
    "hot": 198778
  },
  "AG全员翻拍童年照": {
    "href": "https://s.weibo.com/weibo?q=%23AG%E5%85%A8%E5%91%98%E7%BF%BB%E6%8B%8D%E7%AB%A5%E5%B9%B4%E7%85%A7%23&Refer=top",
    "hot": 198293
  },
  "雅安地震小女孩3分钟两次避险": {
    "href": "https://s.weibo.com/weibo?q=%23%E9%9B%85%E5%AE%89%E5%9C%B0%E9%9C%87%E5%B0%8F%E5%A5%B3%E5%AD%A93%E5%88%86%E9%92%9F%E4%B8%A4%E6%AC%A1%E9%81%BF%E9%99%A9%23&Refer=top",
    "hot": 195520
  },
  "武警官兵紧急驰援芦山地震震区": {
    "href": "https://s.weibo.com/weibo?q=%23%E6%AD%A6%E8%AD%A6%E5%AE%98%E5%85%B5%E7%B4%A7%E6%80%A5%E9%A9%B0%E6%8F%B4%E8%8A%A6%E5%B1%B1%E5%9C%B0%E9%9C%87%E9%9C%87%E5%8C%BA%23&Refer=top",
    "hot": 195286
  },
  "24岁哥哥割三分之一肝脏救8岁弟弟": {
    "href": "https://s.weibo.com/weibo?q=%2324%E5%B2%81%E5%93%A5%E5%93%A5%E5%89%B2%E4%B8%89%E5%88%86%E4%B9%8B%E4%B8%80%E8%82%9D%E8%84%8F%E6%95%918%E5%B2%81%E5%BC%9F%E5%BC%9F%23&Refer=top",
    "hot": 195222
  },
  "中国女排世界联赛首秀": {
    "href": "https://s.weibo.com/weibo?q=%23%E4%B8%AD%E5%9B%BD%E5%A5%B3%E6%8E%92%E4%B8%96%E7%95%8C%E8%81%94%E8%B5%9B%E9%A6%96%E7%A7%80%23&Refer=top",
    "hot": 194030
  },
  "逛吃澳门48小时": {
    "href": "https://s.weibo.com/weibo?q=%23%E9%80%9B%E5%90%83%E6%BE%B3%E9%97%A848%E5%B0%8F%E6%97%B6%23&Refer=top",
    "hot": 192554
  },
  "毕业游总得去趟海边吧": {
    "href": "https://s.weibo.com/weibo?q=%23%E6%AF%95%E4%B8%9A%E6%B8%B8%E6%80%BB%E5%BE%97%E5%8E%BB%E8%B6%9F%E6%B5%B7%E8%BE%B9%E5%90%A7%23&Refer=top",
    "hot": 191391
  },
  "芦山地震最新现场直播": {
    "href": "https://s.weibo.com/weibo?q=%23%E8%8A%A6%E5%B1%B1%E5%9C%B0%E9%9C%87%E6%9C%80%E6%96%B0%E7%8E%B0%E5%9C%BA%E7%9B%B4%E6%92%AD%23&Refer=top",
    "hot": 190872
  },
  "地震局回应雅安3分钟两次地震": {
    "href": "https://s.weibo.com/weibo?q=%23%E5%9C%B0%E9%9C%87%E5%B1%80%E5%9B%9E%E5%BA%94%E9%9B%85%E5%AE%893%E5%88%86%E9%92%9F%E4%B8%A4%E6%AC%A1%E5%9C%B0%E9%9C%87%23&Refer=top",
    "hot": 189614
  },
  "广东端午龙虾粽有多绝": {
    "href": "https://s.weibo.com/weibo?q=%23%E5%B9%BF%E4%B8%9C%E7%AB%AF%E5%8D%88%E9%BE%99%E8%99%BE%E7%B2%BD%E6%9C%89%E5%A4%9A%E7%BB%9D%23&Refer=top",
    "hot": 186591
  },
  "憋尿可能引发不孕不育": {
    "href": "https://s.weibo.com/weibo?q=%23%E6%86%8B%E5%B0%BF%E5%8F%AF%E8%83%BD%E5%BC%95%E5%8F%91%E4%B8%8D%E5%AD%95%E4%B8%8D%E8%82%B2%23&Refer=top",
    "hot": 185240
  },
  "阴阳师": {
    "href": "https://s.weibo.com/weibo?q=%E9%98%B4%E9%98%B3%E5%B8%88&Refer=top",
    "hot": 184037
  },
  "雅安芦山地震已致3人重伤": {
    "href": "https://s.weibo.com/weibo?q=%23%E9%9B%85%E5%AE%89%E8%8A%A6%E5%B1%B1%E5%9C%B0%E9%9C%87%E5%B7%B2%E8%87%B43%E4%BA%BA%E9%87%8D%E4%BC%A4%23&Refer=top",
    "hot": 179790
  },
  "芦山地震与此前汉源地震不在同一断裂带": {
    "href": "https://s.weibo.com/weibo?q=%23%E8%8A%A6%E5%B1%B1%E5%9C%B0%E9%9C%87%E4%B8%8E%E6%AD%A4%E5%89%8D%E6%B1%89%E6%BA%90%E5%9C%B0%E9%9C%87%E4%B8%8D%E5%9C%A8%E5%90%8C%E4%B8%80%E6%96%AD%E8%A3%82%E5%B8%A6%23&Refer=top",
    "hot": 179312
  },
  "2022ChinaJoy线下展延期": {
    "href": "https://s.weibo.com/weibo?q=%232022ChinaJoy%E7%BA%BF%E4%B8%8B%E5%B1%95%E5%BB%B6%E6%9C%9F%23&Refer=top",
    "hot": 176862
  },
  "新华网与跑男团喊你来跳绳": {
    "href": "https://s.weibo.com/weibo?q=%23%E6%96%B0%E5%8D%8E%E7%BD%91%E4%B8%8E%E8%B7%91%E7%94%B7%E5%9B%A2%E5%96%8A%E4%BD%A0%E6%9D%A5%E8%B7%B3%E7%BB%B3%23&Refer=top",
    "hot": 175769
  },
  "美官员哪来的底气勇气颜面对中国指手画脚": {
    "href": "https://s.weibo.com/weibo?q=%23%E7%BE%8E%E5%AE%98%E5%91%98%E5%93%AA%E6%9D%A5%E7%9A%84%E5%BA%95%E6%B0%94%E5%8B%87%E6%B0%94%E9%A2%9C%E9%9D%A2%E5%AF%B9%E4%B8%AD%E5%9B%BD%E6%8C%87%E6%89%8B%E7%94%BB%E8%84%9A%23&Refer=top",
    "hot": 174380
  },
  "刘亦菲古装": {
    "href": "https://s.weibo.com/weibo?q=%23%E5%88%98%E4%BA%A6%E8%8F%B2%E5%8F%A4%E8%A3%85%23&Refer=top",
    "hot": 173871
  },
  "法拉利回应4S店强制加价提车": {
    "href": "https://s.weibo.com/weibo?q=%23%E6%B3%95%E6%8B%89%E5%88%A9%E5%9B%9E%E5%BA%944S%E5%BA%97%E5%BC%BA%E5%88%B6%E5%8A%A0%E4%BB%B7%E6%8F%90%E8%BD%A6%23&Refer=top",
    "hot": 172926
  },
  "87岁老人把刷小学数学题当做升级游戏": {
    "href": "https://s.weibo.com/weibo?q=%2387%E5%B2%81%E8%80%81%E4%BA%BA%E6%8A%8A%E5%88%B7%E5%B0%8F%E5%AD%A6%E6%95%B0%E5%AD%A6%E9%A2%98%E5%BD%93%E5%81%9A%E5%8D%87%E7%BA%A7%E6%B8%B8%E6%88%8F%23&Refer=top",
    "hot": 169967
  },
  "王心凌男孩女孩": {
    "href": "https://s.weibo.com/weibo?q=%23%E7%8E%8B%E5%BF%83%E5%87%8C%E7%94%B7%E5%AD%A9%E5%A5%B3%E5%AD%A9%23&Refer=top",
    "hot": 169031
  },
  "六一上海复工": {
    "href": "https://s.weibo.com/weibo?q=%23%E5%85%AD%E4%B8%80%E4%B8%8A%E6%B5%B7%E5%A4%8D%E5%B7%A5%23&Refer=top",
    "hot": 168333
  },
  "去年我国玩具出口达461亿美元": {
    "href": "https://s.weibo.com/weibo?q=%23%E5%8E%BB%E5%B9%B4%E6%88%91%E5%9B%BD%E7%8E%A9%E5%85%B7%E5%87%BA%E5%8F%A3%E8%BE%BE461%E4%BA%BF%E7%BE%8E%E5%85%83%23&Refer=top",
    "hot": 167551
  },
  "中国足球名宿李松海去世": {
    "href": "https://s.weibo.com/weibo?q=%23%E4%B8%AD%E5%9B%BD%E8%B6%B3%E7%90%83%E5%90%8D%E5%AE%BF%E6%9D%8E%E6%9D%BE%E6%B5%B7%E5%8E%BB%E4%B8%96%23&Refer=top",
    "hot": 161473
  },
  "你小时候用过什么手机": {
    "href": "https://s.weibo.com/weibo?q=%23%E4%BD%A0%E5%B0%8F%E6%97%B6%E5%80%99%E7%94%A8%E8%BF%87%E4%BB%80%E4%B9%88%E6%89%8B%E6%9C%BA%23&Refer=top",
    "hot": 160475
  },
  "太空种菜进展": {
    "href": "https://s.weibo.com/weibo?q=%E5%A4%AA%E7%A9%BA%E7%A7%8D%E8%8F%9C%E8%BF%9B%E5%B1%95&Refer=top",
    "hot": 159007
  },
  "梦华录定档0602": {
    "href": "https://s.weibo.com/weibo?q=%23%E6%A2%A6%E5%8D%8E%E5%BD%95%E5%AE%9A%E6%A1%A30602%23&Refer=top",
    "hot": 157528
  },
  "微博儿童节贴纸上线": {
    "href": "https://s.weibo.com/weibo?q=%E5%BE%AE%E5%8D%9A%E5%84%BF%E7%AB%A5%E8%8A%82%E8%B4%B4%E7%BA%B8%E4%B8%8A%E7%BA%BF&Refer=top",
    "hot": 156691
  },
  "坦克车辆设计专家王哲荣去世": {
    "href": "https://s.weibo.com/weibo?q=%23%E5%9D%A6%E5%85%8B%E8%BD%A6%E8%BE%86%E8%AE%BE%E8%AE%A1%E4%B8%93%E5%AE%B6%E7%8E%8B%E5%93%B2%E8%8D%A3%E5%8E%BB%E4%B8%96%23&Refer=top",
    "hot": 151722
  },
  "公安部新闻发布会": {
    "href": "https://s.weibo.com/weibo?q=%23%E5%85%AC%E5%AE%89%E9%83%A8%E6%96%B0%E9%97%BB%E5%8F%91%E5%B8%83%E4%BC%9A%23&Refer=top",
    "hot": 148573
  },
  "金莎新歌郭襄": {
    "href": "https://s.weibo.com/weibo?q=%23%E9%87%91%E8%8E%8E%E6%96%B0%E6%AD%8C%E9%83%AD%E8%A5%84%23&Refer=top",
    "hot": 147332
  },
  "当下年轻人找乐的新趋势": {
    "href": "https://s.weibo.com/weibo?q=%23%E5%BD%93%E4%B8%8B%E5%B9%B4%E8%BD%BB%E4%BA%BA%E6%89%BE%E4%B9%90%E7%9A%84%E6%96%B0%E8%B6%8B%E5%8A%BF%23&Refer=top",
    "hot": 146482
  },
  "首批10后的最后一个儿童节": {
    "href": "https://s.weibo.com/weibo?q=%23%E9%A6%96%E6%89%B910%E5%90%8E%E7%9A%84%E6%9C%80%E5%90%8E%E4%B8%80%E4%B8%AA%E5%84%BF%E7%AB%A5%E8%8A%82%23&Refer=top",
    "hot": 145030
  },
  "小时候vs长大的我": {
    "href": "https://s.weibo.com/weibo?q=%23%E5%B0%8F%E6%97%B6%E5%80%99vs%E9%95%BF%E5%A4%A7%E7%9A%84%E6%88%91%23&Refer=top",
    "hot": 144038
  },
  "AG童你过六一": {
    "href": "https://s.weibo.com/weibo?q=%23AG%E7%AB%A5%E4%BD%A0%E8%BF%87%E5%85%AD%E4%B8%80%23&Refer=top",
    "hot": 142028
  },
  "乐山3.0级地震": {
    "href": "https://s.weibo.com/weibo?q=%E4%B9%90%E5%B1%B13.0%E7%BA%A7%E5%9C%B0%E9%9C%87&Refer=top",
    "hot": 141592
  },
  "郑业成硬核时代": {
    "href": "https://s.weibo.com/weibo?q=%E9%83%91%E4%B8%9A%E6%88%90%E7%A1%AC%E6%A0%B8%E6%97%B6%E4%BB%A3&Refer=top",
    "hot": 141541
  },
  "当地回应两次未测核酸拘留罚款": {
    "href": "https://s.weibo.com/weibo?q=%23%E5%BD%93%E5%9C%B0%E5%9B%9E%E5%BA%94%E4%B8%A4%E6%AC%A1%E6%9C%AA%E6%B5%8B%E6%A0%B8%E9%85%B8%E6%8B%98%E7%95%99%E7%BD%9A%E6%AC%BE%23&Refer=top",
    "hot": 133534
  },
  "长大后依然被宠爱的瞬间": {
    "href": "https://s.weibo.com/weibo?q=%23%E9%95%BF%E5%A4%A7%E5%90%8E%E4%BE%9D%E7%84%B6%E8%A2%AB%E5%AE%A0%E7%88%B1%E7%9A%84%E7%9E%AC%E9%97%B4%23&Refer=top",
    "hot": 131352
  },
  "喜欢你我也是": {
    "href": "https://s.weibo.com/weibo?q=%E5%96%9C%E6%AC%A2%E4%BD%A0%E6%88%91%E4%B9%9F%E6%98%AF&Refer=top",
    "hot": 128312
  },
  "如何向小朋友介绍中国": {
    "href": "https://s.weibo.com/weibo?q=%E5%A6%82%E4%BD%95%E5%90%91%E5%B0%8F%E6%9C%8B%E5%8F%8B%E4%BB%8B%E7%BB%8D%E4%B8%AD%E5%9B%BD&Refer=top",
    "hot": 127380
  },
  "六一 奖励自己": {
    "href": "https://s.weibo.com/weibo?q=%E5%85%AD%E4%B8%80%20%E5%A5%96%E5%8A%B1%E8%87%AA%E5%B7%B1&Refer=top",
    "hot": 127320
  },
  "成年人的儿童节仪式感": {
    "href": "https://s.weibo.com/weibo?q=%23%E6%88%90%E5%B9%B4%E4%BA%BA%E7%9A%84%E5%84%BF%E7%AB%A5%E8%8A%82%E4%BB%AA%E5%BC%8F%E6%84%9F%23&Refer=top",
    "hot": 124691
  },
  "如何避免儿童接触超龄APP": {
    "href": "https://s.weibo.com/weibo?q=%23%E5%A6%82%E4%BD%95%E9%81%BF%E5%85%8D%E5%84%BF%E7%AB%A5%E6%8E%A5%E8%A7%A6%E8%B6%85%E9%BE%84APP%23&Refer=top",
    "hot": 124476
  },
  "丁程鑫赵今麦花少抓鱼": {
    "href": "https://s.weibo.com/weibo?q=%23%E4%B8%81%E7%A8%8B%E9%91%AB%E8%B5%B5%E4%BB%8A%E9%BA%A6%E8%8A%B1%E5%B0%91%E6%8A%93%E9%B1%BC%23&Refer=top",
    "hot": 124195
  },
  "摄影师相机纪录与妻子相伴抗癌7年": {
    "href": "https://s.weibo.com/weibo?q=%23%E6%91%84%E5%BD%B1%E5%B8%88%E7%9B%B8%E6%9C%BA%E7%BA%AA%E5%BD%95%E4%B8%8E%E5%A6%BB%E5%AD%90%E7%9B%B8%E4%BC%B4%E6%8A%97%E7%99%8C7%E5%B9%B4%23&Refer=top",
    "hot": 124109
  },
  "苹果回应系统偷跑流量": {
    "href": "https://s.weibo.com/weibo?q=%23%E8%8B%B9%E6%9E%9C%E5%9B%9E%E5%BA%94%E7%B3%BB%E7%BB%9F%E5%81%B7%E8%B7%91%E6%B5%81%E9%87%8F%23&Refer=top",
    "hot": 121864
  },
  "董思成给大张伟的祝福有去无回": {
    "href": "https://s.weibo.com/weibo?q=%23%E8%91%A3%E6%80%9D%E6%88%90%E7%BB%99%E5%A4%A7%E5%BC%A0%E4%BC%9F%E7%9A%84%E7%A5%9D%E7%A6%8F%E6%9C%89%E5%8E%BB%E6%97%A0%E5%9B%9E%23&Refer=top",
    "hot": 119855
  },
  "有哪些事必须让孩子知道": {
    "href": "https://s.weibo.com/weibo?q=%23%E6%9C%89%E5%93%AA%E4%BA%9B%E4%BA%8B%E5%BF%85%E9%A1%BB%E8%AE%A9%E5%AD%A9%E5%AD%90%E7%9F%A5%E9%81%93%23&Refer=top",
    "hot": 116329
  },
  "刘大饼": {
    "href": "https://s.weibo.com/weibo?q=%E5%88%98%E5%A4%A7%E9%A5%BC&Refer=top",
    "hot": 110651
  },
  "河南5月31日新增本土确诊2例无症状1例": {
    "href": "https://s.weibo.com/weibo?q=%23%E6%B2%B3%E5%8D%975%E6%9C%8831%E6%97%A5%E6%96%B0%E5%A2%9E%E6%9C%AC%E5%9C%9F%E7%A1%AE%E8%AF%8A2%E4%BE%8B%E6%97%A0%E7%97%87%E7%8A%B61%E4%BE%8B%23&Refer=top",
    "hot": 105924
  },
  "原来豆浆做面条这么好吃": {
    "href": "https://s.weibo.com/weibo?q=%23%E5%8E%9F%E6%9D%A5%E8%B1%86%E6%B5%86%E5%81%9A%E9%9D%A2%E6%9D%A1%E8%BF%99%E4%B9%88%E5%A5%BD%E5%90%83%23&Refer=top",
    "hot": 103795
  },
  "浙江鼓励开展省内跨市游": {
    "href": "https://s.weibo.com/weibo?q=%23%E6%B5%99%E6%B1%9F%E9%BC%93%E5%8A%B1%E5%BC%80%E5%B1%95%E7%9C%81%E5%86%85%E8%B7%A8%E5%B8%82%E6%B8%B8%23&Refer=top",
    "hot": 99045
  },
  "赵露思清唱": {
    "href": "https://s.weibo.com/weibo?q=%23%E8%B5%B5%E9%9C%B2%E6%80%9D%E6%B8%85%E5%94%B1%23&Refer=top",
    "hot": 96457
  },
  "那些记忆里的动画片": {
    "href": "https://s.weibo.com/weibo?q=%23%E9%82%A3%E4%BA%9B%E8%AE%B0%E5%BF%86%E9%87%8C%E7%9A%84%E5%8A%A8%E7%94%BB%E7%89%87%23&Refer=top",
    "hot": 94869
  },
  "直击上海恢复": {
    "href": "https://s.weibo.com/weibo?q=%E7%9B%B4%E5%87%BB%E4%B8%8A%E6%B5%B7%E6%81%A2%E5%A4%8D&Refer=top",
    "hot": 92443
  },
  "四川人的砍价能力有多参差不齐": {
    "href": "https://s.weibo.com/weibo?q=%23%E5%9B%9B%E5%B7%9D%E4%BA%BA%E7%9A%84%E7%A0%8D%E4%BB%B7%E8%83%BD%E5%8A%9B%E6%9C%89%E5%A4%9A%E5%8F%82%E5%B7%AE%E4%B8%8D%E9%BD%90%23&Refer=top",
    "hot": 86438
  },
  "5月31日新增本土确诊22例": {
    "href": "https://s.weibo.com/weibo?q=%235%E6%9C%8831%E6%97%A5%E6%96%B0%E5%A2%9E%E6%9C%AC%E5%9C%9F%E7%A1%AE%E8%AF%8A22%E4%BE%8B%23&Refer=top",
    "hot": 83523
  },
  "王楚钦台球一杆收": {
    "href": "https://s.weibo.com/weibo?q=%23%E7%8E%8B%E6%A5%9A%E9%92%A6%E5%8F%B0%E7%90%83%E4%B8%80%E6%9D%86%E6%94%B6%23&Refer=top",
    "hot": 68675
  },
  "上海将逐步全面恢复个人寄递服务": {
    "href": "https://s.weibo.com/weibo?q=%23%E4%B8%8A%E6%B5%B7%E5%B0%86%E9%80%90%E6%AD%A5%E5%85%A8%E9%9D%A2%E6%81%A2%E5%A4%8D%E4%B8%AA%E4%BA%BA%E5%AF%84%E9%80%92%E6%9C%8D%E5%8A%A1%23&Refer=top",
    "hot": 65117
  },
  "北京昌平新增风险点位发布": {
    "href": "https://s.weibo.com/weibo?q=%23%E5%8C%97%E4%BA%AC%E6%98%8C%E5%B9%B3%E6%96%B0%E5%A2%9E%E9%A3%8E%E9%99%A9%E7%82%B9%E4%BD%8D%E5%8F%91%E5%B8%83%23&Refer=top",
    "hot": 65081
  },
  "中国女排土耳其站14人名单": {
    "href": "https://s.weibo.com/weibo?q=%23%E4%B8%AD%E5%9B%BD%E5%A5%B3%E6%8E%92%E5%9C%9F%E8%80%B3%E5%85%B6%E7%AB%9914%E4%BA%BA%E5%90%8D%E5%8D%95%23&Refer=top",
    "hot": 52294
  },
  "2022世界女排联赛": {
    "href": "https://s.weibo.com/weibo?q=%232022%E4%B8%96%E7%95%8C%E5%A5%B3%E6%8E%92%E8%81%94%E8%B5%9B%23&Refer=top",
    "hot": 26683
  }
}